ZhihuWendaQinshouBaYijiaGongsiNongkuaShiZenyangDeGanjueFix1/README.md
ZhihuWendaQinshouBaYijiaGongsiNongkuaShiZenyangDeGanjueFix1/__init__.py
ZhihuWendaQinshouBaYijiaGongsiNongkuaShiZenyangDeGanjueFix1/__main__.py
ZhihuWendaQinshouBaYijiaGongsiNongkuaShiZenyangDeGanjueFix1/file.epub
ZhihuWendaQinshouBaYijiaGongsiNongkuaShiZenyangDeGanjueFix1/index.html
ZhihuWendaQinshouBaYijiaGongsiNongkuaShiZenyangDeGanjueFix1/css/__init__.py
ZhihuWendaQinshouBaYijiaGongsiNongkuaShiZenyangDeGanjueFix1/css/annotations.css
ZhihuWendaQinshouBaYijiaGongsiNongkuaShiZenyangDeGanjueFix1/css/main.css
ZhihuWendaQinshouBaYijiaGongsiNongkuaShiZenyangDeGanjueFix1/css/normalize.css
ZhihuWendaQinshouBaYijiaGongsiNongkuaShiZenyangDeGanjueFix1/css/popup.css
ZhihuWendaQinshouBaYijiaGongsiNongkuaShiZenyangDeGanjueFix1/font/__init__.py
ZhihuWendaQinshouBaYijiaGongsiNongkuaShiZenyangDeGanjueFix1/font/fontello.eot
ZhihuWendaQinshouBaYijiaGongsiNongkuaShiZenyangDeGanjueFix1/font/fontello.svg
ZhihuWendaQinshouBaYijiaGongsiNongkuaShiZenyangDeGanjueFix1/font/fontello.ttf
ZhihuWendaQinshouBaYijiaGongsiNongkuaShiZenyangDeGanjueFix1/font/fontello.woff
ZhihuWendaQinshouBaYijiaGongsiNongkuaShiZenyangDeGanjueFix1/img/__init__.py
ZhihuWendaQinshouBaYijiaGongsiNongkuaShiZenyangDeGanjueFix1/img/annotator-glyph-sprite.png
ZhihuWendaQinshouBaYijiaGongsiNongkuaShiZenyangDeGanjueFix1/img/annotator-icon-sprite.png
ZhihuWendaQinshouBaYijiaGongsiNongkuaShiZenyangDeGanjueFix1/img/apple-touch-icon.png
ZhihuWendaQinshouBaYijiaGongsiNongkuaShiZenyangDeGanjueFix1/img/cancelfullscreen.png
ZhihuWendaQinshouBaYijiaGongsiNongkuaShiZenyangDeGanjueFix1/img/close.png
ZhihuWendaQinshouBaYijiaGongsiNongkuaShiZenyangDeGanjueFix1/img/fullscreen.png
ZhihuWendaQinshouBaYijiaGongsiNongkuaShiZenyangDeGanjueFix1/img/loader.gif
ZhihuWendaQinshouBaYijiaGongsiNongkuaShiZenyangDeGanjueFix1/img/menu-icon.png
ZhihuWendaQinshouBaYijiaGongsiNongkuaShiZenyangDeGanjueFix1/img/save.png
zhihu_wenda_qinshou_ba_yijia_gongsi_nongkua_shi_zenyang_de_ganjue_fix1-2025.3.24.2.dist-info/METADATA
zhihu_wenda_qinshou_ba_yijia_gongsi_nongkua_shi_zenyang_de_ganjue_fix1-2025.3.24.2.dist-info/WHEEL
zhihu_wenda_qinshou_ba_yijia_gongsi_nongkua_shi_zenyang_de_ganjue_fix1-2025.3.24.2.dist-info/entry_points.txt
zhihu_wenda_qinshou_ba_yijia_gongsi_nongkua_shi_zenyang_de_ganjue_fix1-2025.3.24.2.dist-info/top_level.txt
zhihu_wenda_qinshou_ba_yijia_gongsi_nongkua_shi_zenyang_de_ganjue_fix1-2025.3.24.2.dist-info/RECORD
